{"l":{"a":{"a":{"g":{"e":{"r":{}}}},"b":{"e":{"l":{"l":{"e":{"d":{}},"i":{"n":{"g":{"s":{}}}}},"s":{}}},"i":{"a":{"l":{"s":{}}},"l":{"e":{}},"u":{"m":{}}},"o":{"r":{"a":{"t":{"o":{"r":{"i":{"e":{"s":{}}},"y":{}}}}},"i":{"o":{"u":{"s":{"l":{"y":{}},"n":{"e":{"s":{"s":{}}}}}}}}},"u":{"r":{"e":{"d":{},"r":{"s":{}}},"i":{"n":{"g":{},"t":{"e":{"n":{"s":{"i":{"v":{"e":{}}}}}}}}},"s":{"a":{"v":{"i":{"n":{"g":{}}}}}}}}},"s":{},"u":{"r":{"n":{"u":{"m":{}}}}},"y":{"r":{"i":{"n":{"t":{"h":{"i":{"n":{"e":{}}},"s":{}}}}}}}},"c":{"e":{"d":{},"r":{"a":{"t":{"e":{"d":{}},"i":{"n":{"g":{}},"o":{"n":{"s":{}}}}}}},"s":{},"w":{"o":{"r":{"k":{}}}}},"h":{"e":{"s":{}},"r":{"y":{"m":{"a":{"l":{}},"o":{"s":{"e":{}}}}}}},"i":{"e":{"r":{}},"n":{"g":{"s":{}}}},"k":{"a":{"d":{"a":{"i":{"s":{"i":{"c":{"a":{"l":{}}}}}}}}},"e":{"d":{},"y":{"s":{}}},"i":{"n":{"g":{}}},"l":{"u":{"s":{"t":{"r":{"e":{}}}}}},"s":{}},"o":{"n":{"i":{"c":{"a":{"l":{"l":{"y":{}}}}}}}},"q":{"u":{"e":{"r":{"e":{"d":{}},"s":{}}}}},"r":{"o":{"s":{"s":{"e":{}}}}},"s":{},"t":{"a":{"t":{"e":{},"i":{"o":{"n":{}}}}},"e":{"a":{"l":{}}},"i":{"c":{}},"o":{"s":{"e":{}}}},"u":{"n":{"a":{"e":{},"s":{}}}},"y":{}},"d":{"d":{"e":{"r":{"e":{"d":{}},"s":{}}},"i":{"e":{"s":{}}}},"e":{"n":{}},"i":{"e":{"s":{}},"n":{"g":{}}},"l":{"e":{"d":{},"s":{}},"i":{"n":{"g":{}}}},"s":{},"y":{"b":{"i":{"r":{"d":{"s":{}}}},"u":{"g":{}}},"l":{"i":{"k":{"e":{}}}},"s":{"h":{"i":{"p":{"s":{}}}}}}},"g":{"e":{"r":{"s":{}}},"g":{"a":{"r":{"d":{"s":{}}}},"e":{"d":{}},"i":{"n":{"g":{}}}},"o":{"o":{"n":{"s":{}}},"s":{}},"s":{},"u":{"n":{"e":{}}}},"i":{"d":{},"n":{},"r":{"d":{"s":{}},"s":{}},"s":{"s":{"e":{"z":{"f":{"a":{"i":{"r":{"e":{}}}}}}}}},"t":{"y":{}}},"k":{"e":{"s":{"i":{"d":{"e":{}}}}}},"m":{"a":{"s":{}},"b":{"a":{"s":{"t":{"e":{"d":{}},"i":{"n":{"g":{}}}}}},"d":{"a":{}},"e":{"n":{"t":{}}},"i":{"n":{"g":{}}},"s":{"k":{"i":{"n":{}}},"w":{"o":{"o":{"l":{}}}}}},"e":{"d":{},"l":{"y":{}},"n":{"e":{"s":{"s":{}}},"t":{"a":{"b":{"l":{"e":{},"y":{}}},"t":{"i":{"o":{"n":{"s":{}}}}}},"e":{"d":{},"r":{}},"i":{"n":{"g":{}}},"s":{}}},"s":{"t":{}}},"i":{"n":{"a":{"r":{},"t":{"e":{"d":{},"s":{}},"i":{"o":{"n":{}}}}}}},"p":{"l":{"i":{"g":{"h":{"t":{"e":{"r":{}}}}},"t":{}}},"o":{"o":{"n":{"e":{"d":{},"r":{"y":{}}},"i":{"n":{"g":{}}},"s":{}}}},"p":{"o":{"s":{"t":{"s":{}}}}},"r":{"e":{"y":{"s":{}}}},"s":{"h":{"a":{"d":{"e":{"s":{}}}}}}}},"n":{"c":{"e":{"d":{},"l":{"o":{"t":{}}},"r":{"s":{}},"s":{},"t":{"s":{}}},"i":{"n":{"g":{}}}},"d":{"e":{"d":{},"r":{}},"f":{"a":{"l":{"l":{}}},"i":{"l":{"l":{}}},"o":{"r":{"m":{"s":{}}}}},"h":{"o":{"l":{"d":{"e":{"r":{"s":{}}},"i":{"n":{"g":{"s":{}}}}}}}},"i":{"n":{"g":{"s":{}}}},"l":{"a":{"d":{"i":{"e":{"s":{}}},"y":{}}},"e":{"s":{"s":{}}},"i":{"n":{"e":{"s":{}}}},"o":{"c":{"k":{"e":{"d":{}}}},"r":{"d":{"s":{}}}}},"m":{"a":{"n":{},"r":{"k":{"s":{}}},"s":{"s":{}}},"i":{"n":{"e":{}}}},"o":{"w":{"n":{"e":{"r":{"s":{}}},"i":{"n":{"g":{}}}}}},"s":{"c":{"a":{"p":{"e":{"d":{},"s":{}},"i":{"n":{"g":{}}}}}},"i":{"d":{"e":{}}},"l":{"i":{"d":{"e":{"s":{}}},"p":{"s":{}}}}},"w":{"a":{"r":{"d":{}}}}},"e":{"s":{}},"g":{"u":{"a":{"g":{"e":{"s":{}}}},"i":{"d":{"l":{"y":{}}},"s":{"h":{"e":{"d":{},"s":{}},"i":{"n":{"g":{}}}}}},"o":{"r":{"o":{"u":{"s":{"l":{"y":{}}}}}}}}},"k":{"i":{"e":{"r":{},"s":{"t":{}}}},"y":{}},"o":{"l":{"i":{"n":{}}}},"t":{"e":{"r":{"n":{"s":{}}}}},"y":{"a":{"r":{"d":{}}}}},"o":{"s":{}},"p":{"d":{"o":{"g":{"s":{}}}},"e":{"l":{"s":{}}},"f":{"u":{"l":{}}},"i":{"d":{"a":{"r":{"y":{}}}}},"l":{"a":{"n":{"d":{}}}},"p":{"e":{"d":{}},"i":{"n":{"g":{}}}},"s":{"e":{"d":{},"s":{}},"i":{"n":{"g":{}}}},"t":{"o":{"p":{"s":{}}}},"w":{"i":{"n":{"g":{"s":{}}}}}},"r":{"c":{"e":{"n":{"y":{}}},"h":{"e":{"s":{}}}},"d":{"e":{"r":{"s":{}}},"s":{}},"g":{"e":{"l":{"y":{}},"n":{"e":{"s":{"s":{}}}},"r":{},"s":{"t":{}}},"i":{"s":{"h":{}}},"o":{}},"k":{"i":{"n":{"g":{}}},"s":{}},"v":{"a":{"e":{},"l":{}}},"y":{"n":{"g":{"e":{"a":{"l":{}}},"i":{"t":{"i":{"s":{}}}}},"x":{"e":{"s":{}}}}}},"s":{"a":{"g":{"n":{"e":{}}}},"c":{"i":{"v":{"i":{"o":{"u":{"s":{"l":{"y":{}},"n":{"e":{"s":{"s":{}}}}}}}}}}},"e":{"r":{"s":{}}},"h":{"e":{"d":{},"r":{"s":{}},"s":{}},"i":{"n":{"g":{"s":{}}}}},"i":{"n":{"g":{}}},"s":{"e":{"s":{}},"i":{"e":{"s":{}},"t":{"u":{"d":{"e":{}}}}},"o":{"e":{"d":{}},"i":{"n":{"g":{}}}}},"t":{"e":{"d":{}},"i":{"n":{"g":{}}},"l":{"y":{}},"s":{}}},"t":{"c":{"h":{"e":{"d":{},"s":{}},"i":{"n":{"g":{}}}}},"e":{"c":{"o":{"m":{"e":{"r":{"s":{}}}}}},"l":{"y":{}},"n":{"c":{"i":{"e":{"s":{}}},"y":{}},"e":{"s":{"s":{}}},"t":{}},"r":{"a":{"l":{"i":{"s":{"a":{"t":{"i":{"o":{"n":{}}}}}}},"l":{"y":{}},"s":{}}}},"s":{"t":{}},"x":{}},"h":{"e":{"r":{"e":{"d":{}},"s":{}},"s":{}},"s":{}},"i":{"c":{"e":{"s":{}}},"n":{"o":{}},"t":{"u":{"d":{"e":{"s":{}},"i":{"n":{"a":{"l":{}}}}}}}},"r":{"i":{"n":{"e":{"s":{}}}}},"t":{"e":{"r":{}},"i":{"c":{"e":{"d":{},"s":{}}}}},"v":{"i":{"a":{"n":{}}}}},"u":{"d":{"a":{"b":{"l":{"e":{}}},"t":{"o":{"r":{"y":{}}}}},"e":{"d":{},"r":{"s":{}}},"i":{"n":{"g":{}}},"s":{}},"g":{"h":{"a":{"b":{"l":{"e":{},"y":{}}}},"e":{"d":{},"r":{}},"i":{"n":{"g":{"l":{"y":{}}}}},"s":{},"t":{"e":{"r":{}}}}},"n":{"c":{"h":{"e":{"d":{},"r":{"s":{}},"s":{}},"i":{"n":{"g":{}}}}},"d":{"e":{"r":{"e":{"d":{},"t":{"t":{"e":{"s":{}}}}},"i":{"n":{"g":{}}}}},"r":{"e":{"s":{"s":{}},"t":{"t":{"e":{"s":{}}}}},"i":{"e":{"s":{}}},"y":{}}}},"r":{"e":{"a":{"t":{"e":{}}},"l":{"s":{}}}}},"v":{"a":{"s":{},"t":{"o":{"r":{"i":{"a":{"l":{}},"e":{"s":{}}},"y":{}}}}},"e":{"n":{"d":{"e":{"r":{}}}}},"i":{"s":{"h":{"e":{"d":{},"s":{}},"i":{"n":{"g":{}}},"l":{"y":{}},"n":{"e":{"s":{"s":{}}}}}}}},"w":{"a":{"b":{"i":{"d":{"i":{"n":{"g":{}}}}}}},"b":{"r":{"e":{"a":{"k":{"e":{"r":{"s":{}}},"i":{"n":{"g":{}}}}}}}},"f":{"u":{"l":{"l":{"y":{}},"n":{"e":{"s":{"s":{}}}}}}},"l":{"e":{"s":{"s":{"n":{"e":{"s":{"s":{}}}}}}}},"m":{"a":{"k":{"e":{"r":{"s":{}}}},"n":{}},"e":{"n":{}}},"n":{"m":{"o":{"w":{"e":{"r":{"s":{}}}}}},"s":{}},"s":{"u":{"i":{"t":{"s":{}}}}},"y":{"e":{"r":{"s":{}}}}},"x":{"a":{"t":{"i":{"v":{"e":{"s":{}}}}}},"e":{"r":{}},"i":{"t":{"y":{}}},"n":{"e":{"s":{"s":{}}}}},"y":{"a":{"b":{"o":{"u":{"t":{"s":{}}}}}},"b":{"y":{"s":{}}},"e":{"r":{"e":{"d":{}},"i":{"n":{"g":{}}},"s":{}}},"i":{"n":{"g":{}}},"m":{"a":{"n":{}},"e":{"n":{}}},"o":{"f":{"f":{"s":{}}},"u":{"t":{"s":{}}}},"p":{"e":{"r":{"s":{"o":{"n":{}}}}}},"s":{}},"z":{"a":{"r":{"e":{"t":{}},"u":{"s":{}}}},"e":{"d":{}},"i":{"e":{"r":{},"s":{"t":{}}},"l":{"y":{}},"n":{"e":{"s":{"s":{}}},"g":{}}},"u":{"l":{"i":{}}},"y":{"b":{"o":{"n":{"e":{"s":{}}}}}}}},"e":{"a":{"c":{"h":{"e":{"d":{},"s":{}},"i":{"n":{"g":{}}}}},"d":{"e":{"d":{},"n":{},"r":{"l":{"e":{"s":{"s":{}}}},"s":{"h":{"i":{"p":{"s":{}}}}}}},"f":{"r":{"e":{"e":{}}}},"i":{"n":{"g":{}}},"s":{}},"f":{"e":{"d":{}},"i":{"e":{"r":{},"s":{"t":{}}},"n":{"e":{"s":{"s":{}}},"g":{}}},"l":{"e":{"s":{"s":{}},"t":{"s":{}}}},"y":{}},"g":{"u":{"e":{"s":{}}}},"k":{"a":{"g":{"e":{"s":{}}}},"e":{"d":{}},"i":{"e":{"r":{},"s":{"t":{}}},"n":{"e":{"s":{"s":{}}},"g":{}}},"s":{},"y":{}},"n":{"e":{"d":{},"r":{},"s":{"t":{}}},"i":{"n":{"g":{"s":{}}}},"n":{"e":{"s":{"s":{}}}},"s":{},"t":{}},"p":{"e":{"d":{},"r":{}},"f":{"r":{"o":{"g":{"g":{"i":{"n":{"g":{}}}}}}}},"i":{"n":{"g":{}}},"s":{},"t":{},"y":{"e":{"a":{"r":{}}}}},"r":{"n":{"a":{"b":{"l":{"e":{}}}},"e":{"d":{"l":{"y":{}}},"r":{"s":{}}},"i":{"n":{"g":{}}},"s":{},"t":{}}},"s":{"e":{"d":{},"h":{"o":{"l":{"d":{"e":{"r":{"s":{}}}}}}},"s":{}},"h":{"e":{"d":{},"s":{}},"i":{"n":{"g":{}}}},"i":{"n":{"g":{}}},"t":{}},"t":{"h":{"e":{"r":{"s":{},"y":{}}}}},"v":{"e":{"d":{},"n":{"e":{"d":{}},"i":{"n":{"g":{}}}},"r":{"s":{}},"s":{}},"i":{"n":{"g":{"s":{}}}}}},"b":{"a":{"n":{"o":{"n":{}}}},"e":{"n":{"s":{"r":{"a":{"u":{"m":{}}}}}}}},"c":{"h":{"e":{"r":{"o":{"u":{"s":{"n":{"e":{"s":{"s":{}}}}}}},"y":{}}}},"t":{"e":{"r":{"n":{}}},"o":{"r":{"s":{}}},"u":{"r":{"e":{"d":{},"r":{"s":{}},"s":{"h":{"i":{"p":{"s":{}}}}}},"i":{"n":{"g":{}}}}}}},"d":{"g":{"e":{"r":{"s":{}},"s":{}}}},"e":{"c":{"h":{"e":{"s":{}},"i":{"n":{"g":{}}}}},"d":{"s":{}},"k":{"s":{}},"r":{"e":{"d":{}},"i":{"n":{"g":{"l":{"y":{}}}}},"s":{}},"s":{},"w":{"a":{"r":{"d":{}},"y":{}}}},"f":{"t":{"h":{"a":{"n":{"d":{"e":{"d":{"l":{"y":{}},"n":{"e":{"s":{"s":{}}}}},"r":{"s":{}}}}}}},"i":{"e":{"s":{}},"s":{"h":{},"t":{"s":{}}}},"m":{"o":{"s":{"t":{}}}},"o":{"v":{"e":{"r":{"s":{}}}}},"s":{},"w":{"a":{"r":{"d":{"s":{}}}}},"y":{}}},"g":{"a":{"c":{"i":{"e":{"s":{}}},"y":{}},"l":{"e":{"s":{"e":{}}},"i":{"s":{"a":{"t":{"i":{"o":{"n":{}}}}},"e":{"d":{}},"i":{"n":{"g":{}}},"m":{},"t":{"i":{"c":{}}}},"t":{"i":{"e":{"s":{}}},"y":{}}},"l":{"y":{}}},"t":{"e":{"e":{"s":{}},"s":{}},"i":{"o":{"n":{}}},"o":{"r":{}}}},"e":{"n":{"d":{"a":{"r":{"y":{}}},"s":{}}},"r":{"d":{"e":{"m":{"a":{"i":{"n":{}}}}}}}},"g":{"e":{"d":{}},"i":{"n":{"g":{"s":{}}}},"y":{}},"h":{"o":{"r":{"n":{"s":{}}}}},"i":{"b":{"i":{"l":{"i":{"t":{"y":{}}}}},"l":{"e":{},"y":{}}},"o":{"n":{"a":{"r":{"i":{"e":{"s":{}}},"y":{}}},"n":{"a":{"i":{"r":{"e":{"s":{}}}}}},"s":{}}},"s":{"l":{"a":{"t":{"e":{"d":{}},"i":{"n":{"g":{}},"o":{"n":{}},"v":{"e":{"l":{"y":{}}}}},"o":{"r":{"s":{}}},"u":{"r":{"e":{"s":{}}}}}}}},"t":{"i":{"m":{"a":{"c":{"y":{}},"t":{"e":{"d":{},"l":{"y":{}}},"i":{"n":{"g":{}},"o":{"n":{}}}}},"i":{"s":{"a":{"t":{"i":{"o":{"n":{}}}}},"e":{"d":{}},"i":{"n":{"g":{}}}}}}}}},"l":{"e":{"s":{"s":{}}}},"m":{"a":{"n":{}}},"r":{"o":{"o":{"m":{}}}},"s":{},"u":{"m":{"e":{"s":{}},"i":{"n":{"o":{"u":{"s":{}}}}}}},"w":{"o":{"r":{"k":{}}}}},"i":{"p":{"z":{"i":{"g":{}}}},"s":{"u":{"r":{"e":{"d":{},"l":{"y":{}},"w":{"e":{"a":{"r":{}}}}}}}},"t":{"m":{"o":{"t":{"i":{"f":{"s":{}},"v":{"s":{}}}}}}}},"m":{"m":{"a":{"s":{}},"i":{"n":{"g":{"s":{}}}}},"o":{"n":{"a":{"d":{"e":{}}},"s":{}}},"u":{"r":{"s":{}}}},"n":{"d":{"e":{"r":{"s":{}}},"i":{"n":{"g":{}}},"s":{}},"g":{"t":{"h":{"e":{"n":{"e":{"d":{}},"i":{"n":{"g":{}}},"s":{}}},"i":{"e":{"r":{},"s":{"t":{}}},"l":{"y":{}}},"s":{},"w":{"a":{"y":{"s":{}}},"i":{"s":{"e":{}}}},"y":{}}}},"i":{"e":{"n":{"c":{"y":{}},"t":{"l":{"y":{}}}}},"n":{}},"s":{"e":{"s":{}},"i":{"n":{"g":{}}}},"t":{"i":{"l":{"s":{}}},"o":{}}},"o":{"n":{"a":{"r":{"d":{"o":{}}}},"e":{}},"p":{"a":{"r":{"d":{"s":{"k":{"i":{"n":{}}}}}}}},"t":{"a":{"r":{"d":{"s":{}}}}}},"p":{"e":{"r":{"s":{}}},"r":{"e":{"c":{"h":{"a":{"u":{"n":{"s":{}}}}}}},"o":{"s":{"e":{},"y":{}},"u":{"s":{}}}},"t":{"o":{"n":{"s":{}}}}},"s":{"b":{"i":{"a":{"n":{"i":{"s":{"m":{}}},"s":{}}}}},"i":{"o":{"n":{"s":{}}}},"o":{"t":{"h":{"o":{}}}},"s":{"e":{"e":{"s":{}},"n":{"e":{"d":{}},"i":{"n":{"g":{}}},"s":{}},"r":{}},"o":{"n":{"s":{}},"r":{"s":{}}}},"t":{}},"t":{"h":{"a":{"l":{"i":{"t":{"y":{}}},"l":{"y":{}}},"r":{"g":{"i":{"c":{"a":{"l":{"l":{"y":{}}}}}},"y":{}}}}},"s":{},"t":{"e":{"r":{"b":{"o":{"x":{"e":{"s":{}}}}},"e":{"d":{}},"h":{"e":{"a":{"d":{"s":{}}}}},"i":{"n":{"g":{}}},"p":{"r":{"e":{"s":{"s":{}}}}},"s":{},"w":{"r":{"i":{"t":{"e":{"r":{}}}}}}}},"i":{"n":{"g":{"s":{}}},"s":{"h":{}}},"u":{"c":{"e":{"s":{}}}}}},"u":{"c":{"i":{"n":{"e":{}}}},"k":{"a":{"e":{"m":{"i":{"a":{}}}}},"e":{"m":{"i":{"a":{}}}}}},"v":{"e":{"l":{"h":{"e":{"a":{"d":{"e":{"d":{}}}}}},"l":{"e":{"d":{},"r":{}},"i":{"n":{"g":{}}},"y":{}},"s":{}},"r":{"a":{"g":{"e":{"d":{}}}},"e":{"d":{}},"i":{"n":{"g":{}}},"s":{}}},"i":{"a":{"t":{"h":{"a":{"n":{}}}}},"e":{"d":{},"s":{}},"t":{"a":{"t":{"e":{"d":{},"s":{}},"i":{"n":{"g":{}},"o":{"n":{}}}}},"y":{}}},"y":{"i":{"n":{"g":{}}}}},"w":{"d":{"n":{"e":{"s":{"s":{}}}}}},"x":{"e":{"m":{"e":{"s":{}}}},"i":{"c":{"a":{"l":{"l":{"y":{}}}},"o":{"g":{"r":{"a":{"p":{"h":{"e":{"r":{"s":{}}},"i":{"c":{"a":{"l":{"l":{"y":{}}}}}},"y":{}}}}}},"n":{"s":{}}}}}},"y":{"d":{"e":{"n":{}}}}},"i":{"a":{"b":{"i":{"l":{"i":{"t":{"i":{"e":{"s":{}}},"y":{}}}}},"l":{"e":{}}},"i":{"s":{"e":{"d":{},"s":{}},"i":{"n":{"g":{}}},"o":{"n":{"s":{}}}}},"r":{"s":{}}},"b":{"a":{"t":{"i":{"o":{"n":{"s":{}}}}}},"e":{"l":{"e":{"d":{},"r":{}},"l":{"e":{"d":{},"r":{}},"i":{"n":{"g":{}}},"o":{"u":{"s":{}}}},"s":{}},"r":{"a":{"l":{"i":{"s":{"a":{"t":{"i":{"o":{"n":{}}}}},"e":{"d":{}},"i":{"n":{"g":{}}},"m":{}},"t":{"y":{}}},"l":{"y":{}},"s":{}},"t":{"e":{"d":{},"s":{}},"i":{"n":{"g":{}},"o":{"n":{"i":{"s":{"t":{"s":{}}}}}}},"o":{"r":{"s":{}}}}},"i":{"a":{}},"o":{},"t":{"a":{"r":{"i":{"a":{"n":{"i":{"s":{"m":{}}},"s":{}}}}}},"i":{"e":{"s":{}},"n":{"e":{"s":{}}}},"y":{}}}},"i":{"d":{"i":{"n":{"o":{"u":{"s":{}}}}},"o":{}}},"r":{"a":{"r":{"i":{"a":{"n":{"s":{"h":{"i":{"p":{}}}}}},"e":{"s":{}}},"y":{}},"t":{"e":{"d":{},"s":{}}}},"e":{"t":{"t":{"i":{"s":{"t":{"s":{}}}},"o":{}}}}},"y":{"a":{"n":{"s":{}}}}},"c":{"e":{"n":{"c":{"e":{"s":{}}},"s":{"e":{"d":{},"e":{"s":{}},"s":{}},"i":{"n":{"g":{}}}},"t":{"i":{"a":{"t":{"e":{}}},"o":{"u":{"s":{"n":{"e":{"s":{"s":{}}}}}}}}}}},"h":{"e":{"e":{},"n":{"e":{"d":{}},"s":{}}},"i":{"s":{}}},"k":{"e":{"d":{},"r":{"i":{"s":{"h":{}}}}},"i":{"n":{"g":{}}},"s":{}},"o":{"r":{"i":{"c":{"e":{}}}}}},"d":{"d":{"e":{"d":{}}},"l":{"e":{"s":{"s":{}}}},"o":{},"s":{}},"e":{"d":{"e":{"r":{}}},"n":{"s":{}},"s":{},"u":{"t":{"e":{"n":{"a":{"n":{"c":{"y":{}},"t":{"s":{}}}}}}}}},"f":{"e":{"a":{"n":{"d":{"d":{"e":{"a":{"t":{"h":{}}}}}}}},"b":{"e":{"l":{"t":{}}},"l":{"o":{"o":{"d":{}}}},"o":{"a":{"t":{"m":{"e":{"n":{}}},"s":{}}}}},"f":{"o":{"r":{"m":{"s":{}}}}},"g":{"i":{"v":{"i":{"n":{"g":{}}}}},"u":{"a":{"r":{"d":{"s":{}}}}}},"l":{"e":{"s":{"s":{"l":{"y":{}},"n":{"e":{"s":{"s":{}}}}}}},"i":{"k":{"e":{}},"n":{"e":{"s":{}}}},"o":{"n":{"g":{}}}},"r":{"a":{"f":{"t":{"s":{}}}}},"s":{"a":{"v":{"i":{"n":{"g":{}}}}},"i":{"z":{"e":{"d":{}}}},"p":{"a":{"n":{"s":{}}}},"t":{"y":{"l":{"e":{"s":{}}}}}},"t":{"a":{"k":{"i":{"n":{"g":{}}}}},"h":{"r":{"e":{"a":{"t":{"e":{"n":{"i":{"n":{"g":{}}}}}}}}}},"i":{"m":{"e":{"s":{}}}}},"w":{"o":{"r":{"k":{}}}}},"t":{"e":{"d":{},"r":{"s":{}}},"i":{"n":{"g":{}}},"m":{"a":{"n":{}},"e":{"n":{}}},"o":{"f":{"f":{}}},"s":{}}},"g":{"a":{"m":{"e":{"n":{"t":{"s":{}}}}},"n":{"d":{"s":{}}},"t":{"u":{"r":{"e":{"d":{},"s":{}},"i":{"n":{"g":{}}}}}}},"h":{"t":{"e":{"d":{},"n":{"e":{"d":{}},"i":{"n":{"g":{}}},"s":{}},"r":{"s":{}},"s":{"t":{}}},"h":{"e":{"a":{"d":{"e":{"d":{"n":{"e":{"s":{"s":{}}}}}}},"r":{"t":{"e":{"d":{"l":{"y":{}},"n":{"e":{"s":{"s":{}}}}}}}}}},"o":{"u":{"s":{"e":{"s":{}}}}}},"i":{"n":{"g":{}}},"l":{"e":{"s":{"s":{}}},"y":{}},"n":{"e":{"s":{"s":{}}},"i":{"n":{"g":{}}}},"s":{"h":{"i":{"p":{}}}},"w":{"e":{"i":{"g":{"h":{"t":{"s":{}}}}}}}}},"n":{"i":{"t":{"e":{}}}}},"k":{"a":{"b":{"l":{"e":{}}}},"e":{"a":{"b":{"i":{"l":{"i":{"t":{"y":{}}}}},"l":{"e":{}}}},"d":{},"l":{"i":{"e":{"r":{},"s":{"t":{}}},"h":{"o":{"o":{"d":{}}}}},"y":{}},"m":{"i":{"n":{"d":{"e":{"d":{}}}}}},"n":{"e":{"d":{},"s":{"s":{"e":{"s":{}}}}},"i":{"n":{"g":{}}},"s":{}},"s":{},"w":{"i":{"s":{"e":{}}}}},"i":{"n":{"g":{"s":{}}}}},"l":{"a":{"c":{"s":{}}},"i":{"e":{"s":{}}},"l":{"i":{"p":{"u":{"t":{"i":{"a":{"n":{}}}}}}}},"o":{"n":{"g":{"w":{"e":{}}}}},"t":{"i":{"n":{"g":{}}}},"y":{"l":{"i":{"v":{"e":{"r":{"e":{"d":{}}}}}}},"w":{"h":{"i":{"t":{"e":{}}}}}}},"m":{"a":{},"b":{"e":{"r":{"i":{"n":{"g":{}}},"s":{}}},"l":{"e":{"s":{"s":{}}}},"o":{},"s":{}},"e":{"k":{"i":{"l":{"n":{}}}},"l":{"i":{"g":{"h":{"t":{}}}}},"r":{"i":{"c":{"k":{"s":{}}}}},"s":{"t":{"o":{"n":{"e":{"s":{}}}}}},"y":{"s":{}}},"i":{"n":{"a":{"l":{}},"g":{}},"t":{"a":{"t":{"i":{"o":{"n":{"s":{}}}}}},"e":{"d":{},"r":{"s":{}}},"i":{"n":{"g":{}}},"l":{"e":{"s":{"s":{}}}},"s":{}}},"o":{"u":{"s":{"i":{"n":{"e":{"s":{}}}}}}},"p":{"e":{"d":{},"t":{"s":{}}},"i":{"d":{},"n":{"g":{}}},"l":{"y":{}},"o":{"p":{"o":{}}},"s":{}}},"n":{"a":{"g":{"e":{}}},"c":{"h":{"p":{"i":{"n":{}}}},"o":{"l":{"n":{}}}},"d":{"e":{"n":{}}},"e":{"a":{"g":{"e":{"s":{}}},"l":{"l":{"y":{}}},"m":{"e":{"n":{"t":{"s":{}}}}},"r":{"i":{"s":{"e":{"d":{}}},"t":{"y":{}}},"l":{"y":{}}}},"d":{},"f":{"e":{"e":{"d":{}}}},"m":{"a":{"n":{}},"e":{"n":{}}},"n":{"s":{}},"o":{"u":{"t":{"s":{}}}},"r":{"s":{}},"s":{"m":{"a":{"n":{}},"e":{"n":{}}}},"u":{"p":{"s":{}}}},"g":{"e":{"r":{"e":{"d":{},"r":{}},"i":{"e":{},"n":{"g":{"l":{"y":{}}}}},"s":{}}},"u":{"a":{"l":{}},"i":{"s":{"t":{"i":{"c":{"a":{"l":{"l":{"y":{}}}},"s":{}}},"s":{}}}}}},"i":{"m":{"e":{"n":{"t":{"s":{}}}}},"n":{"g":{"s":{}}}},"k":{"a":{"b":{"l":{"e":{}}},"g":{"e":{"s":{}}}},"e":{"d":{},"r":{"s":{}}},"i":{"n":{"g":{}}},"s":{},"u":{"p":{"s":{}}}},"n":{"e":{"t":{"s":{}}}},"o":{"l":{"e":{"u":{"m":{}}}}},"s":{"e":{"e":{"d":{}}}},"t":{"e":{"l":{"s":{}}}},"y":{}},"o":{"n":{"e":{"s":{"s":{"e":{"s":{}}}}},"i":{"s":{"e":{"d":{}}}},"s":{}}},"p":{"a":{"s":{"e":{}}},"i":{"d":{"s":{}}},"p":{"e":{"d":{}}},"r":{"e":{"a":{"d":{"i":{"n":{"g":{}}}}}}},"s":{"e":{"r":{"v":{"i":{"c":{"e":{}}}}}},"t":{"i":{"c":{"k":{"s":{}}}}}}},"q":{"u":{"e":{"f":{"a":{"c":{"t":{"i":{"o":{"n":{}}}}}},"i":{"e":{"d":{}}},"y":{}},"u":{"r":{"s":{}}}},"i":{"d":{"a":{"t":{"e":{"d":{}},"i":{"n":{"g":{}},"o":{"n":{"s":{}}}},"o":{"r":{"s":{}}}}},"i":{"s":{"e":{"d":{},"r":{}},"i":{"n":{"g":{}}}},"t":{"y":{}}},"s":{}},"f":{"y":{}}},"o":{"r":{"i":{"c":{"e":{}},"s":{"h":{}}},"s":{}}}}},"r":{"a":{},"e":{}},"s":{"b":{"o":{"n":{}}},"p":{"e":{"d":{}},"i":{"n":{"g":{}}},"s":{}},"s":{"o":{"m":{"e":{"n":{"e":{"s":{"s":{}}}}},"n":{"e":{"s":{"s":{}}}}}}},"t":{"e":{"d":{},"n":{"e":{"d":{},"r":{"s":{}}},"i":{"n":{"g":{}}},"s":{}},"r":{"i":{"a":{}}}},"i":{"n":{"g":{"s":{}}}},"l":{"e":{"s":{"s":{"l":{"y":{}},"n":{"e":{"s":{"s":{}}}}}}}},"s":{}}},"t":{"a":{"n":{"i":{"e":{"s":{}}},"y":{}}},"c":{"h":{"i":{}}},"e":{"r":{"a":{"c":{"y":{}},"l":{"i":{"s":{"m":{},"t":{"i":{"c":{}}}}},"l":{"y":{}},"s":{}},"r":{"y":{}},"t":{"e":{},"i":{},"u":{"r":{"e":{"s":{}}}}}}}},"h":{"e":{"l":{"y":{}}},"i":{"u":{"m":{}}},"o":{"g":{"r":{"a":{"p":{"h":{"i":{"c":{}},"s":{},"y":{}}}}}},"l":{"o":{"g":{"i":{"c":{"a":{"l":{}}},"e":{"s":{}}},"y":{}}}},"s":{"p":{"h":{"e":{"r":{"e":{}}}}}}}},"i":{"g":{"a":{"n":{"t":{"s":{}}},"t":{"e":{},"i":{"n":{"g":{}},"o":{"n":{}}}}},"i":{"o":{"u":{"s":{"n":{"e":{"s":{"s":{}}}}}}}}}},"m":{"u":{"s":{}}},"o":{"t":{"e":{"s":{}}}},"r":{"e":{"s":{}}},"t":{"e":{"r":{"e":{"d":{}},"i":{"n":{"g":{}}},"s":{}}},"l":{"e":{"n":{"e":{"s":{"s":{}}}},"r":{},"s":{"t":{}}}},"o":{"r":{"a":{"l":{}}}}},"u":{"r":{"g":{"i":{"c":{"a":{"l":{}}},"e":{"s":{}}},"y":{}}}}},"v":{"a":{"b":{"l":{"e":{}}}},"e":{"a":{"b":{"l":{"e":{}}}},"d":{},"l":{"i":{"e":{"r":{},"s":{"t":{}}},"h":{"o":{"o":{"d":{"s":{}}}}},"n":{"e":{"s":{"s":{}}}}},"y":{}},"n":{"e":{"d":{}},"i":{"n":{"g":{}}},"s":{}},"r":{"i":{"e":{"d":{},"s":{}},"s":{"h":{}}},"s":{},"w":{"o":{"r":{"t":{"s":{}}}}},"y":{}},"s":{"t":{"o":{"c":{"k":{}}}}},"w":{"i":{"r":{"e":{}}}}},"i":{"d":{"l":{"y":{}}},"n":{"g":{"s":{}}}}},"z":{"a":{"r":{"d":{"s":{}}}}}},"l":{"a":{"m":{"a":{"s":{}}}},"s":{}},"o":{"a":{"d":{"a":{"b":{"l":{"e":{}}}},"e":{"d":{},"r":{"s":{}}},"i":{"n":{"g":{"s":{}}}},"s":{}},"f":{"e":{"d":{},"r":{"s":{}}},"i":{"n":{"g":{}}},"s":{}},"m":{"s":{},"y":{}},"n":{"a":{"b":{"l":{"e":{}}}},"e":{"d":{},"r":{}},"i":{"n":{"g":{}}},"s":{},"w":{"o":{"r":{"d":{"s":{}}}}}},"t":{"h":{"e":{"d":{},"s":{}},"i":{"n":{"g":{}}},"s":{"o":{"m":{"e":{"l":{"y":{}},"n":{"e":{"s":{"s":{}}}}}}}}}},"v":{"e":{"s":{}}}},"b":{"b":{"e":{"d":{}},"i":{"e":{"d":{},"s":{}},"n":{"g":{}}},"y":{"i":{"n":{"g":{}},"s":{"t":{"s":{}}}}}},"e":{"d":{},"l":{"i":{"a":{}}},"s":{}},"o":{"t":{"o":{"m":{"i":{"e":{"s":{}},"s":{"e":{"d":{}},"i":{"n":{"g":{}}},"t":{}}},"y":{}}}}},"s":{"t":{"e":{"r":{"s":{}}}}},"u":{"l":{"a":{"r":{}}}}},"c":{"a":{"l":{"e":{"s":{}},"i":{"s":{"a":{"t":{"i":{"o":{"n":{"s":{}}}}}},"e":{"d":{},"s":{}},"i":{"n":{"g":{}}}},"t":{"i":{"e":{"s":{}}},"y":{}}},"l":{"y":{}},"s":{}},"t":{"a":{"b":{"l":{"e":{}}}},"e":{"d":{},"s":{}},"i":{"n":{"g":{}},"o":{"n":{"a":{"l":{}},"s":{}}},"v":{"e":{}}},"o":{"r":{"s":{}}}}},"h":{"n":{"e":{"s":{"s":{}}}},"s":{}},"i":{},"k":{"a":{"b":{"l":{"e":{}}},"g":{"e":{}}},"e":{"d":{},"r":{"s":{}},"t":{}},"i":{"n":{"g":{}}},"j":{"a":{"w":{}}},"o":{"u":{"t":{"s":{}}}},"s":{"m":{"i":{"t":{"h":{}}}}}},"o":{"m":{"o":{"t":{"e":{},"i":{"o":{"n":{}},"v":{"e":{"s":{}}}}}}}},"u":{"s":{"t":{"s":{}}}}},"d":{"e":{"s":{"t":{"a":{"r":{}},"o":{"n":{"e":{}}}}}},"g":{"e":{"d":{},"m":{"e":{"n":{"t":{}}}},"r":{"s":{}},"s":{}},"i":{"n":{"g":{"s":{}}}}}},"e":{"s":{"s":{}}},"f":{"t":{"e":{"d":{}},"i":{"e":{"r":{},"s":{"t":{}}},"l":{"y":{}},"n":{"e":{"s":{"s":{}}}}},"s":{},"y":{}}},"g":{"a":{"n":{"b":{"e":{"r":{"r":{"i":{"e":{"s":{}}},"y":{}}}}}},"r":{"i":{"t":{"h":{"m":{"i":{"c":{"a":{"l":{"l":{"y":{}}}}}},"s":{}}}}}}},"b":{"o":{"o":{"k":{"s":{}}}}},"g":{"e":{"d":{},"r":{"h":{"e":{"a":{"d":{"s":{}}}}},"s":{}}},"i":{"n":{"g":{}}}},"i":{"c":{"a":{"l":{"i":{"t":{"y":{}}},"l":{"y":{}}}},"i":{"a":{"n":{"s":{}}}},"s":{}},"s":{"t":{"i":{"c":{"a":{"l":{"l":{"y":{}}}},"s":{}}}}}},"j":{"a":{"m":{}}},"o":{"f":{"f":{}},"s":{}},"s":{}},"i":{"n":{"c":{"l":{"o":{"t":{"h":{}}}}},"s":{}},"r":{"e":{}},"t":{"e":{"r":{"e":{"d":{},"r":{"s":{}}},"i":{"n":{"g":{}}},"s":{}}}}},"l":{"l":{"e":{"d":{}},"i":{"e":{"s":{}},"n":{"g":{}},"p":{"o":{"p":{"s":{}}}}},"y":{}}},"n":{"d":{"o":{"n":{"e":{"r":{}}}}},"e":{"l":{"i":{"e":{"r":{},"s":{"t":{}}},"n":{"e":{"s":{"s":{}}}}},"y":{}},"r":{"s":{}},"s":{"o":{"m":{"e":{"n":{"e":{"s":{"s":{}}}}}}}}},"g":{"a":{"w":{"a":{"i":{"t":{"e":{"d":{}}}}}}},"e":{"d":{},"r":{},"s":{"t":{}},"v":{"i":{"t":{"y":{}}}}},"f":{"a":{"c":{"e":{"d":{}}}}},"h":{"a":{"n":{"d":{}}}},"i":{"n":{"g":{"l":{"y":{}},"s":{}}},"s":{"h":{}},"t":{"u":{"d":{"e":{"s":{}},"i":{"n":{"a":{"l":{"l":{"y":{}}}}}}}}}},"l":{"a":{"s":{"t":{"i":{"n":{"g":{}}}}}},"i":{"v":{"e":{"d":{}}}},"o":{"s":{"t":{}}}},"s":{"t":{"a":{"n":{"d":{"i":{"n":{"g":{}}}}}}},"u":{"f":{"f":{"e":{"r":{"i":{"n":{"g":{}}}}}}}}},"w":{"i":{"n":{"d":{"e":{"d":{"n":{"e":{"s":{"s":{}}}}}}}}}}}},"o":{"k":{"a":{"l":{"i":{"k":{"e":{"s":{}}}}}},"e":{"d":{},"r":{"s":{}}},"i":{"n":{"g":{"g":{"l":{"a":{"s":{"s":{"e":{"s":{}}}}}}}}}},"o":{"u":{"t":{"s":{}}}},"s":{}},"m":{"e":{"d":{}},"i":{"n":{"g":{}}},"s":{}},"n":{"e":{"y":{}},"y":{}},"p":{"e":{"d":{}},"h":{"o":{"l":{"e":{"s":{}}}}},"i":{"n":{"g":{}}},"s":{},"y":{}},"s":{"e":{"d":{},"l":{"y":{}},"n":{"e":{"d":{},"s":{"s":{}}},"i":{"n":{"g":{}}},"s":{}},"r":{},"s":{"t":{}}},"i":{"n":{"g":{}}}},"t":{"e":{"d":{},"r":{"s":{}}},"i":{"n":{"g":{}}},"s":{}}},"p":{"e":{"d":{},"s":{}},"i":{"n":{"g":{}}},"p":{"e":{"d":{},"r":{"s":{}}},"i":{"n":{"g":{}}}},"s":{"i":{"d":{"e":{"d":{"l":{"y":{}}}}}}}},"q":{"u":{"a":{"c":{"i":{"o":{"u":{"s":{}}},"t":{"y":{}}}}}}},"r":{"d":{"i":{"n":{"g":{}}},"l":{"y":{}},"s":{"h":{"i":{"p":{"s":{}}}}}},"e":{"l":{"e":{"i":{}}}},"r":{"i":{"e":{"s":{}}},"y":{"l":{"o":{"a":{"d":{"s":{}}}}}}}},"s":{"a":{"b":{"l":{"e":{}}}},"e":{"r":{"s":{}},"s":{}},"i":{"n":{"g":{"s":{}}}},"s":{"e":{"s":{}}},"t":{}},"t":{"h":{},"i":{"o":{"n":{"s":{}}}},"s":{},"t":{"e":{"r":{"i":{"e":{"s":{}}},"y":{}}},"o":{}},"u":{"s":{}}},"u":{"c":{"h":{"e":{}}},"d":{"e":{"r":{},"s":{"t":{}}},"h":{"a":{"i":{"l":{"e":{"r":{"s":{}}}}}}},"l":{"y":{}},"m":{"o":{"u":{"t":{"h":{"e":{"d":{}}}}}}},"n":{"e":{"s":{"s":{}}}},"s":{"p":{"e":{"a":{"k":{"e":{"r":{"s":{}}}}}}}}},"i":{"s":{}},"n":{"g":{"e":{"d":{},"r":{"s":{}},"s":{}},"i":{"n":{"g":{}}}}},"s":{"e":{},"i":{"e":{"s":{"t":{}}},"l":{"y":{}}},"y":{}},"t":{"i":{"s":{"h":{"n":{"e":{"s":{"s":{}}}}}}},"s":{}},"v":{"e":{"r":{"s":{}}},"r":{"e":{"d":{},"s":{}}}}},"v":{"a":{"b":{"l":{"e":{}}}},"e":{"a":{"b":{"l":{"e":{}}}},"b":{"i":{"r":{"d":{"s":{}}}}},"d":{},"l":{"e":{"s":{"s":{}}},"i":{"e":{"r":{},"s":{"t":{}}},"n":{"e":{"s":{"s":{}}}}},"o":{"r":{"n":{}}},"y":{}},"m":{"a":{"k":{"i":{"n":{"g":{}}}}}},"r":{"s":{}},"s":{"i":{"c":{"k":{}}},"t":{"r":{"u":{"c":{"k":{}}}}}}},"i":{"n":{"g":{"l":{"y":{}}}}}},"w":{"e":{"r":{"c":{"a":{"s":{"e":{}}}},"e":{"d":{}},"i":{"n":{"g":{}}},"s":{}},"s":{"t":{}}},"i":{"n":{"g":{}},"s":{"h":{}}},"k":{"e":{"y":{}}},"l":{"a":{"n":{"d":{"e":{"r":{"s":{}}},"s":{}}}},"i":{"e":{"r":{},"s":{"t":{}}}},"y":{"i":{"n":{"g":{}}}}},"n":{"e":{"s":{"s":{}}}},"p":{"i":{"t":{"c":{"h":{"e":{"d":{}}}}}}},"s":{"p":{"i":{"r":{"i":{"t":{"e":{"d":{}}}}}}}}},"y":{"a":{"l":{"i":{"s":{"t":{"s":{}}}},"l":{"y":{}},"t":{"i":{"e":{"s":{}}},"y":{}}}}},"z":{"e":{"n":{"g":{"e":{"s":{}}}}}}},"u":{"a":{"n":{"d":{"a":{}}}},"b":{"b":{"e":{"r":{"s":{}}}},"r":{"i":{"c":{"a":{"n":{"t":{"s":{}}},"t":{"e":{"d":{},"s":{}},"i":{"n":{"g":{}},"o":{"n":{}}}}},"i":{"o":{"u":{"s":{}}}}}}}},"c":{"i":{"d":{"i":{"t":{"y":{}}},"l":{"y":{}}},"f":{"e":{"r":{}}}},"k":{"i":{"e":{"r":{},"s":{"t":{}}},"l":{"y":{}}},"l":{"e":{"s":{"s":{}}}},"y":{}},"r":{"a":{"t":{"i":{"v":{"e":{}}}}},"e":{}}},"d":{"i":{"c":{"r":{"o":{"u":{"s":{"l":{"y":{}},"n":{"e":{"s":{"s":{}}}}}}}}}},"o":{}},"g":{"g":{"a":{"g":{"e":{}}},"e":{"d":{}},"i":{"n":{"g":{}}}},"s":{},"u":{"b":{"r":{"i":{"o":{"u":{"s":{"l":{"y":{}}}}}}}}}},"k":{"e":{"w":{"a":{"r":{"m":{}}}}}},"l":{"l":{"a":{"b":{"i":{"e":{"s":{}}},"y":{}}},"e":{"d":{}},"i":{"n":{"g":{}}},"s":{}},"u":{}},"m":{"b":{"a":{"g":{"o":{}},"r":{}},"e":{"r":{"e":{"d":{}},"i":{"n":{"g":{}}},"j":{"a":{"c":{"k":{"s":{}}}}},"s":{}}}},"e":{"n":{}},"i":{"n":{"a":{"l":{},"n":{"c":{"e":{}}},"r":{"i":{"e":{"s":{}}},"y":{}}},"e":{"s":{"c":{"e":{"n":{"c":{"e":{}},"t":{}}}}}},"o":{"s":{"i":{"t":{"i":{"e":{"s":{}}},"y":{}}}},"u":{"s":{"l":{"y":{}}}}}}},"p":{"e":{"d":{},"n":{}},"i":{"e":{"r":{},"s":{"t":{}}},"n":{"e":{"s":{"s":{}}},"g":{}},"s":{"h":{}}},"s":{},"y":{}}},"n":{"a":{"c":{"i":{"e":{"s":{}}},"y":{}},"r":{},"t":{"e":{},"i":{"c":{"s":{}}}}},"c":{"h":{"e":{"d":{},"o":{"n":{"s":{}}},"r":{"s":{}},"s":{}},"i":{"n":{"g":{}}},"p":{"a":{"c":{"k":{}}}},"t":{"i":{"m":{"e":{"s":{}}}}}}},"e":{},"g":{"e":{"d":{},"s":{}},"f":{"i":{"s":{"h":{}}},"u":{"l":{"s":{}}}},"i":{"n":{"g":{}}},"s":{}}},"p":{"i":{"n":{"e":{"s":{}},"s":{}}}},"r":{"c":{"h":{"e":{"d":{},"r":{"s":{}},"s":{}},"i":{"n":{"g":{}}}}},"e":{"d":{},"s":{},"x":{}},"i":{"d":{"l":{"y":{}}},"n":{"g":{}}},"k":{"e":{"d":{},"r":{"s":{}}},"i":{"n":{"g":{}}},"s":{}}},"s":{"a":{"k":{"a":{}}},"c":{"i":{"o":{"u":{"s":{"l":{"y":{}}}}}}},"h":{"e":{"r":{},"s":{"t":{}}},"n":{"e":{"s":{"s":{}}}}},"t":{"e":{"d":{}},"f":{"u":{"l":{"l":{"y":{}}}}},"i":{"e":{"r":{},"s":{"t":{}}},"l":{"y":{}},"n":{"g":{}}},"r":{"e":{"l":{"e":{"s":{"s":{}}}}},"o":{"u":{"s":{}}}},"s":{},"y":{}}},"t":{"e":{"s":{}},"h":{"e":{"r":{}}}},"x":{"o":{"r":{}},"u":{"r":{"i":{"a":{"n":{"c":{"e":{}},"t":{"l":{"y":{}}}},"t":{"e":{},"i":{"n":{"g":{}}}}},"e":{"s":{}},"o":{"u":{"s":{"l":{"y":{}}}}}},"y":{}}}}},"y":{"c":{"h":{"e":{"e":{"s":{}}}}},"e":{},"i":{"n":{"g":{}}},"m":{"p":{"h":{"a":{"t":{"i":{"c":{}}}},"o":{"c":{"y":{"t":{"e":{"s":{}},"i":{"c":{}}}}},"i":{"d":{}},"m":{"a":{"s":{}}}}}}},"n":{"c":{"h":{"e":{"d":{},"s":{}},"i":{"n":{"g":{}}},"p":{"i":{"n":{}}}}},"x":{"e":{"s":{}}}},"o":{"n":{"s":{}}},"r":{"a":{},"e":{"s":{}},"i":{"c":{"a":{"l":{"l":{"y":{}}}},"i":{"s":{"m":{},"t":{"s":{}}}},"s":{}},"s":{"t":{}}}},"s":{"i":{"n":{"e":{}}}}}}}